src/example_package_zhaohany/_init_.py
src/example_package_zhaohany/example.py
example_package_zhaohany-0.0.2.dist-info/METADATA
example_package_zhaohany-0.0.2.dist-info/WHEEL
example_package_zhaohany-0.0.2.dist-info/licenses/LICENSE
example_package_zhaohany-0.0.2.dist-info/RECORD
