Metadata-Version: 2.1
Name: example_package_zhaohany
Version: 0.0.2
Summary: A small example package
Project-URL: Homepage, https://github.com/zhaohany/example_package_zhaohany
Project-URL: Bug Tracker, https://github.com/zhaohany/example_package_zhaohany
Author-email: Zhaohan Yan <zhaohany@outlook.com>
License-File: LICENSE
Classifier: License :: OSI Approved :: MIT License
Classifier: Operating System :: OS Independent
Classifier: Programming Language :: Python :: 3
Requires-Python: >=3.7
